[{"Krankheit": "Herzinsuffizienz", "Ursachen": {"Frage": "Welche Ursachen hat ein/e Herzinsuffizienz?", "Antworten": {"Arterielle Hypertonie": "right", "Koronare Herzkrankheit (KHK)": "right", "Mitralstenose": "right", "Herzmuskelentzündung": "right", "akute Appendizitis": "wrong", "Herzrhythmusstörungen": "right"}}, "Komplikationen": {"Frage": "Welche Komplikationen können bei einer/m Herzinsuffizienz auftreten?", "Antworten": {"Arterielle Embolien": "wrong", "Kardiogener Schock": "right", "Thrombophlebitis": "wrong", "Phlebothrombose": "right", "Herzwandaneurysma mit Rupturgefahr": "wrong", "Lungenödem": "right"}}, "Diagnostiken": {"Frage": "Welche Diagnostiken nutzt man bei einer/m Herzinsuffizienz?", "Antworten": {"Blutuntersuchung": "right", "D-Dimer-Bestimmung": "wrong", "EKG": "right", "Röntgen Thorax": "right", "Trendelenburg (Funktionstest)": "wrong", "Echokardiographie": "right"}}, "Therapien": {"Frage": "Welche Therapien nutzt man bei einer/m Herzinsuffizienz?", "Antworten": {"Therapie der KHK": "right", "Kochsalzreduktion": "right", "Nahrungs- und Flüssigkeitskarenz": "wrong", "Limitierung der Flüssigkeitszufuhr": "right", "Diuretika": "right", "Schonung": "right"}}}]