<quiz><question type="category"><category><text>$course$/Krankheitslehrefragen(2021.01.30_13:33)</text></category></question><question type="category"><category><text>$course$/Krankheitslehrefragen(2021.01.30_13:33)</text></category></question><question type="multichoice"><name><text>Herzrhythmusst&#246;rungen (Ursachen)</text></name><questiontext format="html"><text>Welche Ursachen hat ein/e Herzrhythmusst&#246;rungen &lt;u&gt;nicht&lt;/u&gt;?</text></questiontext><defaultgrade>6</defaultgrade><single>false</single><shuffleanswers>true</shuffleanswers><answernumbering>none</answernumbering><correctfeedback format="html"><text>Die Antwort ist richtig</text></correctfeedback><partiallycorrrectfeedback format="html"><text>Die Antwort ist teilweise richtig</text></partiallycorrrectfeedback><incorrectfeedback format="html"><text>Die Antwort ist falsch</text></incorrectfeedback><answer format="html" fraction="-25.0"><text>Medikamente</text></answer><answer format="html" fraction="-25.0"><text>Koronare Herzkrankheit (KHK)</text></answer><answer format="html" fraction="-25.0"><text>Nikotin</text></answer><answer format="html" fraction="-25.0"><text>Myokardinfarkt</text></answer><answer format="html" fraction="100.0"><text>Flussbehinderung in den Gallenwegen (durch Stenosen, Tumore)</text></answer><answer format="html" fraction="-25.0"><text>Elektrolytst&#246;rungen</text></answer></question><question type="multichoice"><name><text>Herzrhythmusst&#246;rungen (Symptome)</text></name><questiontext format="html"><text>Welche Symptome treten bei einer/m Herzrhythmusst&#246;rungen &lt;u&gt;nicht&lt;/u&gt; auf?</text></questiontext><defaultgrade>6</defaultgrade><single>false</single><shuffleanswers>true</shuffleanswers><answernumbering>none</answernumbering><correctfeedback format="html"><text>Die Antwort ist richtig</text></correctfeedback><partiallycorrrectfeedback format="html"><text>Die Antwort ist teilweise richtig</text></partiallycorrrectfeedback><incorrectfeedback format="html"><text>Die Antwort ist falsch</text></incorrectfeedback><answer format="html" fraction="20.0"><text>Ulzera</text></answer><answer format="html" fraction="20.0"><text>Gewichtszunahme</text></answer><answer format="html" fraction="20.0"><text>R&#246;tlich gef&#228;rbtes Sputum</text></answer><answer format="html" fraction="20.0"><text>Brummen (bei Ausatmung)</text></answer><answer format="html" fraction="20.0"><text>Lungenstauung</text></answer><answer format="html" fraction="-25.0"><text>Sprachst&#246;rungen</text></answer></question><question type="multichoice"><name><text>Herzrhythmusst&#246;rungen (Komplikationen)</text></name><questiontext format="html"><text>Welche Komplikationen k&#246;nnen bei einer/m Herzrhythmusst&#246;rungen &lt;u&gt;nicht&lt;/u&gt; auftreten?</text></questiontext><defaultgrade>6</defaultgrade><single>false</single><shuffleanswers>true</shuffleanswers><answernumbering>none</answernumbering><correctfeedback format="html"><text>Die Antwort ist richtig</text></correctfeedback><partiallycorrrectfeedback format="html"><text>Die Antwort ist teilweise richtig</text></partiallycorrrectfeedback><incorrectfeedback format="html"><text>Die Antwort ist falsch</text></incorrectfeedback><answer format="html" fraction="-25.0"><text>Herzinsuffizienz</text></answer><answer format="html" fraction="25.0"><text>Ulcus cruris</text></answer><answer format="html" fraction="25.0"><text>Thrombose bei Bewegungsmangel</text></answer><answer format="html" fraction="25.0"><text>Arteriosklerotische Aneurysmen</text></answer><answer format="html" fraction="-25.0"><text>Myokardinfarkt</text></answer><answer format="html" fraction="25.0"><text>Thromboserezediv</text></answer></question><question type="multichoice"><name><text>Herzrhythmusst&#246;rungen (Diagnostiken)</text></name><questiontext format="html"><text>Welche Diagnostiken nutzt man bei einer/m Herzrhythmusst&#246;rungen &lt;u&gt;nicht&lt;/u&gt;?</text></questiontext><defaultgrade>6</defaultgrade><single>false</single><shuffleanswers>true</shuffleanswers><answernumbering>none</answernumbering><correctfeedback format="html"><text>Die Antwort ist richtig</text></correctfeedback><partiallycorrrectfeedback format="html"><text>Die Antwort ist teilweise richtig</text></partiallycorrrectfeedback><incorrectfeedback format="html"><text>Die Antwort ist falsch</text></incorrectfeedback><answer format="html" fraction="-25.0"><text>Ruhe-EKG</text></answer><answer format="html" fraction="-25.0"><text>Belastungs-EKG</text></answer><answer format="html" fraction="-25.0"><text>Langzeit-EKG</text></answer><answer format="html" fraction="100.0"><text>Phlebographie</text></answer><answer format="html" fraction="-25.0"><text>Symptome (Anamnese)</text></answer><answer format="html" fraction="-25.0"><text>Elektrophysiologische Untersuchung</text></answer></question><question type="multichoice"><name><text>Herzrhythmusst&#246;rungen (Therapien)</text></name><questiontext format="html"><text>Welche Therapien nutzt man bei einer/m Herzrhythmusst&#246;rungen &lt;u&gt;nicht&lt;/u&gt;?</text></questiontext><defaultgrade>6</defaultgrade><single>false</single><shuffleanswers>true</shuffleanswers><answernumbering>none</answernumbering><correctfeedback format="html"><text>Die Antwort ist richtig</text></correctfeedback><partiallycorrrectfeedback format="html"><text>Die Antwort ist teilweise richtig</text></partiallycorrrectfeedback><incorrectfeedback format="html"><text>Die Antwort ist falsch</text></incorrectfeedback><answer format="html" fraction="-25.0"><text>Defibrillation</text></answer><answer format="html" fraction="50.0"><text>Linksherzkatheter mit PTCA</text></answer><answer format="html" fraction="-25.0"><text>Herzschrittmacher</text></answer><answer format="html" fraction="50.0"><text>Bronchienerweiternde Medikamente</text></answer><answer format="html" fraction="-25.0"><text>Katheterablation</text></answer><answer format="html" fraction="-25.0"><text>Defibrillatorimplantation</text></answer></question><question type="multichoice"><name><text>Koronare Herzkrankheit (KHK)</text></name><questiontext format="html"><text>Welche Krankheiten k&#246;nnen aus der Ursache Koronare Herzkrankheit (KHK) entstehen?</text></questiontext><defaultgrade>6</defaultgrade><single>false</single><shuffleanswers>true</shuffleanswers><answernumbering>none</answernumbering><correctfeedback format="html"><text>Die Antwort ist richtig</text></correctfeedback><partiallycorrrectfeedback format="html"><text>Die Antwort ist teilweise richtig</text></partiallycorrrectfeedback><incorrectfeedback format="html"><text>Die Antwort ist falsch</text></incorrectfeedback><answer format="html" fraction="33.333333333333336"><text>Myokardinfarkt</text></answer><answer format="html" fraction="33.333333333333336"><text>Herzrhythmusst&#246;rungen</text></answer><answer format="html" fraction="-25.0"><text>Periphere arterielle Verschlusskrankheit (pAVK)</text></answer><answer format="html" fraction="33.333333333333336"><text>Herzinsuffizienz</text></answer><answer format="html" fraction="-25.0"><text>Varikosis (Krampfaderleiden)</text></answer><answer format="html" fraction="-25.0"><text>Arteriosklerose</text></answer></question><question type="multichoice"><name><text>Niedriger Blutdruck</text></name><questiontext format="html"><text>Bei welchen Krankheiten tritt das Symptom Niedriger Blutdruck auf?</text></questiontext><defaultgrade>6</defaultgrade><single>false</single><shuffleanswers>true</shuffleanswers><answernumbering>none</answernumbering><correctfeedback format="html"><text>Die Antwort ist richtig</text></correctfeedback><partiallycorrrectfeedback format="html"><text>Die Antwort ist teilweise richtig</text></partiallycorrrectfeedback><incorrectfeedback format="html"><text>Die Antwort ist falsch</text></incorrectfeedback><answer format="html" fraction="-25.0"><text>Gallensteinerkrankung</text></answer><answer format="html" fraction="-25.0"><text>Myokardinfarkt</text></answer><answer format="html" fraction="50.0"><text>Herzklappenfehler</text></answer><answer format="html" fraction="-25.0"><text>Varikosis (Krampfaderleiden)</text></answer><answer format="html" fraction="-25.0"><text>Herzrhythmusst&#246;rungen</text></answer><answer format="html" fraction="50.0"><text>Herzinsuffizienz</text></answer></question><question type="multichoice"><name><text>Kompressionsstr&#252;mpfe</text></name><questiontext format="html"><text>Bei welchen Krankheiten hilft die Therapie Kompressionsstr&#252;mpfe?</text></questiontext><defaultgrade>6</defaultgrade><single>false</single><shuffleanswers>true</shuffleanswers><answernumbering>none</answernumbering><correctfeedback format="html"><text>Die Antwort ist richtig</text></correctfeedback><partiallycorrrectfeedback format="html"><text>Die Antwort ist teilweise richtig</text></partiallycorrrectfeedback><incorrectfeedback format="html"><text>Die Antwort ist falsch</text></incorrectfeedback><answer format="html" fraction="50.0"><text>Phlebothrombose</text></answer><answer format="html" fraction="50.0"><text>Varikosis (Krampfaderleiden)</text></answer><answer format="html" fraction="-25.0"><text>Koronare Herzkrankheit (KHK)</text></answer><answer format="html" fraction="-25.0"><text>Herzklappenfehler</text></answer><answer format="html" fraction="-25.0"><text>Myokardinfarkt</text></answer><answer format="html" fraction="-25.0"><text>Periphere arterielle Verschlusskrankheit (pAVK)</text></answer></question><question type="multichoice"><name><text>Herzrhythmusst&#246;rungen</text></name><questiontext format="html"><text>Bei welchen Krankheiten kommt es zu der Komplikation Herzrhythmusst&#246;rungen?</text></questiontext><defaultgrade>6</defaultgrade><single>false</single><shuffleanswers>true</shuffleanswers><answernumbering>none</answernumbering><correctfeedback format="html"><text>Die Antwort ist richtig</text></correctfeedback><partiallycorrrectfeedback format="html"><text>Die Antwort ist teilweise richtig</text></partiallycorrrectfeedback><incorrectfeedback format="html"><text>Die Antwort ist falsch</text></incorrectfeedback><answer format="html" fraction="50.0"><text>Koronare Herzkrankheit (KHK)</text></answer><answer format="html" fraction="-25.0"><text>Varikosis (Krampfaderleiden)</text></answer><answer format="html" fraction="-25.0"><text>Arteriosklerose</text></answer><answer format="html" fraction="-25.0"><text>Periphere arterielle Verschlusskrankheit (pAVK)</text></answer><answer format="html" fraction="50.0"><text>Herzinsuffizienz</text></answer><answer format="html" fraction="-25.0"><text>Magen- und Zw&#246;lffingerdarmgeschw&#252;r</text></answer></question><question type="multichoice"><name><text>Keine Symptome</text></name><questiontext format="html"><text>Bei welchen Krankheiten tritt das Symptom Keine Symptome auf?</text></questiontext><defaultgrade>6</defaultgrade><single>false</single><shuffleanswers>true</shuffleanswers><answernumbering>none</answernumbering><correctfeedback format="html"><text>Die Antwort ist richtig</text></correctfeedback><partiallycorrrectfeedback format="html"><text>Die Antwort ist teilweise richtig</text></partiallycorrrectfeedback><incorrectfeedback format="html"><text>Die Antwort ist falsch</text></incorrectfeedback><answer format="html" fraction="100.0"><text>Herzrhythmusst&#246;rungen</text></answer><answer format="html" fraction="-25.0"><text>Varikosis (Krampfaderleiden)</text></answer><answer format="html" fraction="-25.0"><text>Periphere arterielle Verschlusskrankheit (pAVK)</text></answer><answer format="html" fraction="-25.0"><text>Myokardinfarkt</text></answer><answer format="html" fraction="-25.0"><text>Phlebothrombose</text></answer><answer format="html" fraction="-25.0"><text>Akutes Abdomen</text></answer></question></quiz>